koala_analytics/__init__.py
koala_analytics/connectors/__init__.py
koala_analytics/connectors/bq_connector.py
koala_analytics/metrics/__init__.py
koala_analytics/metrics/base_metrics.py
koala_analytics/metrics/influxdb_metrics.py
koala_analytics/metrics/prometheus_metrics.py
koala_analytics-0.0.3.dist-info/METADATA
koala_analytics-0.0.3.dist-info/WHEEL
koala_analytics-0.0.3.dist-info/top_level.txt
koala_analytics-0.0.3.dist-info/RECORD
